dcm_classify/README.md
dcm_classify/__init__.py
dcm_classify/dicom_config.py
dcm_classify/dicom_series.py
dcm_classify/dicom_validator.py
dcm_classify/dicom_volume.py
dcm_classify/image_type_inference.py
dcm_classify/namic_dicom_typing.py
dcm_classify/study_processing.py
dcm_classify-0.0.1.dist-info/METADATA
dcm_classify-0.0.1.dist-info/WHEEL
dcm_classify-0.0.1.dist-info/RECORD
