Metadata-Version: 2.1
Name: dcm_classify
Version: 0.0.1
Summary: This is a consolidation of work from NAMIC efforts primarily at the University of Iowa.
Author-email: Michal Brzus <author@example.com>
Classifier: License :: OSI Approved :: MIT License
Classifier: Operating System :: OS Independent
Classifier: Programming Language :: Python :: 3
Requires-Python: >=3.7
